[{"name": "BIOAQUA SERUM CERAMIDE", "price": 48000}, {"name": "BIOAQUA SERUM CERAMIDE", "price": 48000}, {"name": "BIOAQUA SHEET MASK CALENDULA 28GR", "price": 6000}, {"name": "BIOAQUA SHEET MASK CHAMOMILE 25GR", "price": 6000}, {"name": "BIOAQUA SHEET MASK KIWI 25GR", "price": 6000}, {"name": "BIOAQUA SHEET MASK LILY 28G", "price": 6000}, {"name": "BIORE BF CLEAR FRESH 250ML", "price": 16900}, {"name": "BIORE BF ENERGETIC COOL 250ML", "price": 20000}, {"name": "BIORE BF LIVELY REFRESH 250ML", "price": 20000}, {"name": "BIORE BF LIVELY REFRESH BTL 100ML", "price": 12000}]